django_multimedia-0.2.0.dist-info/top_level.txt
django_multimedia-0.2.0.dist-info/RECORD
django_multimedia-0.2.0.dist-info/METADATA
django_multimedia-0.2.0.dist-info/WHEEL
django_multimedia-0.2.0.dist-info/metadata.json
django_multimedia-0.2.0.dist-info/DESCRIPTION.rst
multimedia/signals.py
multimedia/__init__.py
multimedia/utils.py
multimedia/tasks.py
multimedia/admin.py
multimedia/compat.py
multimedia/models.py
multimedia/tests/settings.py
multimedia/tests/factories.py
multimedia/tests/__init__.py
multimedia/tests/test_models.py
multimedia/south_migrations/0019_auto__add_remotestorage.py
multimedia/south_migrations/0027_auto__del_field_encodeprofile_file_type.py
multimedia/south_migrations/0014_add_encodeprofile_move_audio_move_video.py
multimedia/south_migrations/0003_auto__add_mediabase__add_audio__add_video.py
multimedia/south_migrations/0011_auto__add_field_video_generated_thumbnail.py
multimedia/south_migrations/0002_auto__add_field_media_thumbnail_image__add_field_media_auto_thumbnail_.py
multimedia/south_migrations/0020_auto__del_field_audio_encoding__del_field_audio_encoded__del_field_vid.py
multimedia/south_migrations/0017_auto__del_field_audio_uploaded__del_field_video_uploaded.py
multimedia/south_migrations/0025_auto__del_field_media_slug.py
multimedia/south_migrations/0021_auto__add_media__add_field_encodeprofile_file_type.py
multimedia/south_migrations/0008_auto__del_field_video_generated_thumbnail.py
multimedia/south_migrations/0016_auto__del_videoprev__del_mediabase__del_audioprev.py
multimedia/south_migrations/0015_move_from_mediabase.py
multimedia/south_migrations/0022_move_media.py
multimedia/south_migrations/0009_auto__add_field_mediabase_encoding.py
multimedia/south_migrations/0004_auto__add_field_mediabase_profile.py
multimedia/south_migrations/0026_auto__chg_field_remotestorage_media.py
multimedia/south_migrations/0013_auto__del_field_video_custom_thumb__del_field_video_auto_thumb__del_fi.py
multimedia/south_migrations/__init__.py
multimedia/south_migrations/0010_auto__del_media.py
multimedia/south_migrations/0006_auto__add_field_mediabase_encoded_file.py
multimedia/south_migrations/0028_auto__add_field_media_active.py
