Metadata-Version: 2.0
Name: django-multimedia
Version: 0.2.0
Summary: Encode and upload multimedia from the Django admin interface
Home-page: https://github.com/jbittel/django-multimedia
Author: Jason Bittel
Author-email: jason.bittel@gmail.com
License: BSD
Download-URL: https://pypi.python.org/pypi/django-multimedia/
Keywords: multimedia,media,audio,video,encoding,conversion
Platform: UNKNOWN
Classifier: Development Status :: 3 - Alpha
Classifier: Environment :: Web Environment
Classifier: Framework :: Django
Classifier: License :: OSI Approved :: BSD License
Classifier: Intended Audience :: Developers
Classifier: Operating System :: OS Independent
Classifier: Programming Language :: Python
Classifier: Topic :: Multimedia :: Video
Classifier: Topic :: Multimedia :: Video :: Conversion
Classifier: Topic :: Multimedia :: Sound/Audio
Classifier: Topic :: Multimedia :: Sound/Audio :: Conversion
Classifier: Topic :: Software Development :: Libraries :: Python Modules
Requires-Dist: celery (>=3.1)
Requires-Dist: django-storages
